TeraboxDL/__init__.py
TeraboxDL/__version__.py
TeraboxDL/teraboxdl.py
terabox_downloader-1.7.dist-info/licenses/LICENSE
terabox_downloader-1.7.dist-info/METADATA
terabox_downloader-1.7.dist-info/WHEEL
terabox_downloader-1.7.dist-info/top_level.txt
terabox_downloader-1.7.dist-info/RECORD
