Metadata-Version: 2.4
Name: terabox-downloader
Version: 1.7
Summary: TeraboxDL is a Python package for interacting with Terabox, enabling you to fetch file details such as name, download link, thumbnail, and size, and download files with support for custom progress tracking via a callback function.
Home-page: https://github.com/Damantha126/TeraboxDL
Author: DamanthaJasinghe
Author-email: damanthaja@gmail.com
License: MIT
Project-URL: Community, https://t.me/SDBOTs_inifinity
Keywords: terabox,python-package,terabox-bypass,terabox-downloader,damanthaja,mritzme,damantha126,direct-download,jasinghe,damantha-jasinghe
Classifier: Programming Language :: Python :: 3
Classifier: License :: OSI Approved :: MIT License
Classifier: Operating System :: OS Independent
Requires-Python: >=3.7
License-File: LICENSE
Requires-Dist: requests
Dynamic: author
Dynamic: author-email
Dynamic: classifier
Dynamic: description
Dynamic: description-content-type
Dynamic: home-page
Dynamic: keywords
Dynamic: license
Dynamic: license-file
Dynamic: project-url
Dynamic: requires-dist
Dynamic: requires-python
Dynamic: summary
